Oyemi/__init__.py
Oyemi/distance.py
Oyemi/encoder.py
Oyemi/exceptions.py
Oyemi/storage.py
data/lexicon.db
oyemi-3.2.0.dist-info/licenses/LICENSE
oyemi-3.2.0.dist-info/METADATA
oyemi-3.2.0.dist-info/WHEEL
oyemi-3.2.0.dist-info/top_level.txt
oyemi-3.2.0.dist-info/RECORD
