Metadata-Version: 2.4
Name: oyemi
Version: 3.2.0
Summary: Offline semantic numeric lexicon - deterministic word-to-code mapping
Author: Kaossara Osseni
License: MIT
Project-URL: Homepage, https://github.com/Osseni94/Oyemi
Project-URL: Repository, https://github.com/Osseni94/Oyemi.git
Project-URL: Issues, https://github.com/Osseni94/Oyemi/issues
Keywords: nlp,semantics,lexicon,wordnet,encoding,word-embedding,deterministic
Classifier: Development Status :: 4 - Beta
Classifier: Intended Audience :: Developers
Classifier: Intended Audience :: Science/Research
Classifier: License :: OSI Approved :: MIT License
Classifier: Operating System :: OS Independent
Classifier: Programming Language :: Python :: 3
Classifier: Programming Language :: Python :: 3.8
Classifier: Programming Language :: Python :: 3.9
Classifier: Programming Language :: Python :: 3.10
Classifier: Programming Language :: Python :: 3.11
Classifier: Programming Language :: Python :: 3.12
Classifier: Topic :: Scientific/Engineering :: Artificial Intelligence
Classifier: Topic :: Text Processing :: Linguistic
Requires-Python: >=3.8
License-File: LICENSE
Provides-Extra: build
Requires-Dist: nltk>=3.8; extra == "build"
Requires-Dist: tqdm>=4.60; extra == "build"
Provides-Extra: dev
Requires-Dist: pytest>=7.0; extra == "dev"
Requires-Dist: pytest-cov>=4.0; extra == "dev"
Requires-Dist: black>=23.0; extra == "dev"
Requires-Dist: mypy>=1.0; extra == "dev"
Dynamic: license-file
